testman/__init__.py
testman/__main__.py
testman/cli.py
testman/state.py
testman/store.py
testman/util.py
testman/testers/__init__.py
testman/testers/mail.py
testman/testers/mock.py
testman/unwrap/__init__.py
testman/unwrap/requests.py
tests/__init__.py
tests/test_command.py
tests/test_constant.py
tests/test_example.py
tests/test_step.py
tests/test_util.py
testman-0.0.7.dist-info/LICENSE.txt
testman-0.0.7.dist-info/METADATA
testman-0.0.7.dist-info/WHEEL
testman-0.0.7.dist-info/entry_points.txt
testman-0.0.7.dist-info/top_level.txt
testman-0.0.7.dist-info/RECORD
