Metadata-Version: 2.1
Name: testman
Version: 0.0.7
Summary: A manager for automated testing by humans
Home-page: https://github.com/christophevg/testman
Author: Christophe VG
License: MIT
Keywords: manager testing human
Platform: UNKNOWN
Classifier: Programming Language :: Python :: 3
Classifier: Programming Language :: Python :: 3.8
Classifier: Development Status :: 4 - Beta
Classifier: Intended Audience :: Developers
Requires-Dist: pyyaml
Requires-Dist: dotmap
Requires-Dist: fire
Requires-Dist: python-dotenv
Requires-Dist: pymongo
